{"_ts":[1598921209,1599101240],"_r":{"breakdown":{"html":{"bytes":[8392,8385],"requests":[4,3]},"js":{"bytes":[270131,270318],"requests":[9,9]},"css":{"bytes":[23333,23333],"requests":[6,6]},"image":{"bytes":[1618346,1618311],"requests":[22,21]},"flash":{"bytes":[0,0],"requests":[0,0]},"font":{"bytes":[28964,28964],"requests":[2,2]},"video":{"bytes":[0,0],"requests":[0,0]},"other":{"bytes":[0,3],"requests":[0,2]}},"date":[1598921209,1599101240],"domElements":[172,172],"domInteractive":[1807.5,1220.5],"firstPaint":[1782.709999999497,1207.575000000361],"fullyLoaded":[5514.5,4928],"id":["200901_1S_db9cc97b1becd93a6dcdc4dd38eefce1","200903_4C_f8a4749a0dab453846ea371537924eb3"],"loadTime":[5353.5,4532],"render":[1950,1300],"SpeedIndex":[2040,1334.5],"TTFB":[1076.5,506],"videoFrames":[[{"_i":"ms_000000.jpg","_t":0,"_vc":0},{"_i":"ms_001800.jpg","_t":1800,"_vc":99},{"_i":"ms_001900.jpg","_t":1900,"_vc":99},{"_i":"ms_002000.jpg","_t":2000,"_vc":99},{"_i":"ms_002200.jpg","_t":2200,"_vc":99},{"_i":"ms_002400.jpg","_t":2400,"_vc":100}],[{"_i":"ms_000000.jpg","_t":0,"_vc":0},{"_i":"ms_001300.jpg","_t":1300,"_vc":95},{"_i":"ms_001400.jpg","_t":1400,"_vc":98},{"_i":"ms_001500.jpg","_t":1500,"_vc":98},{"_i":"ms_001600.jpg","_t":1600,"_vc":98},{"_i":"ms_001700.jpg","_t":1700,"_vc":98},{"_i":"ms_001800.jpg","_t":1800,"_vc":100}]],"visualComplete":[2450,1850],"lighthouse":[null,44],"pagespeed":[null,null]}}